odoo/addons/l10n_fr_chorus_sale/README.rst
odoo/addons/l10n_fr_chorus_sale/__init__.py
odoo/addons/l10n_fr_chorus_sale/__manifest__.py
odoo/addons/l10n_fr_chorus_sale/i18n/fr.po
odoo/addons/l10n_fr_chorus_sale/i18n/l10n_fr_chorus_sale.pot
odoo/addons/l10n_fr_chorus_sale/models/__init__.py
odoo/addons/l10n_fr_chorus_sale/models/sale_order.py
odoo/addons/l10n_fr_chorus_sale/readme/CONTRIBUTORS.rst
odoo/addons/l10n_fr_chorus_sale/readme/DESCRIPTION.rst
odoo/addons/l10n_fr_chorus_sale/readme/USAGE.rst
odoo/addons/l10n_fr_chorus_sale/static/description/icon.png
odoo/addons/l10n_fr_chorus_sale/static/description/index.html
odoo/addons/l10n_fr_chorus_sale/views/sale_order.xml
odoo12_addon_l10n_fr_chorus_sale-12.0.1.0.2.dist-info/METADATA
odoo12_addon_l10n_fr_chorus_sale-12.0.1.0.2.dist-info/WHEEL
odoo12_addon_l10n_fr_chorus_sale-12.0.1.0.2.dist-info/top_level.txt
odoo12_addon_l10n_fr_chorus_sale-12.0.1.0.2.dist-info/RECORD
